{
  "/_not-found/page": "app/_not-found/page.js",
  "/alerts/page": "app/alerts/page.js",
  "/billing/page": "app/billing/page.js",
  "/applications/new/page": "app/applications/new/page.js",
  "/applications/page": "app/applications/page.js",
  "/calendar/page": "app/calendar/page.js",
  "/design/[id]/page": "app/design/[id]/page.js",
  "/dashboard/page": "app/dashboard/page.js",
  "/design/[id]/print/page": "app/design/[id]/print/page.js",
  "/design/page": "app/design/page.js",
  "/expenses/new/page": "app/expenses/new/page.js",
  "/entities/page": "app/entities/page.js",
  "/forgot-password/page": "app/forgot-password/page.js",
  "/export/page": "app/export/page.js",
  "/expenses/page": "app/expenses/page.js",
  "/get-paid/page": "app/get-paid/page.js",
  "/income/page": "app/income/page.js",
  "/leases/[id]/edit/page": "app/leases/[id]/edit/page.js",
  "/leases/page": "app/leases/page.js",
  "/leases/new/page": "app/leases/new/page.js",
  "/listings/page": "app/listings/page.js",
  "/leases/[id]/page": "app/leases/[id]/page.js",
  "/login/page": "app/login/page.js",
  "/maintenance/[id]/page": "app/maintenance/[id]/page.js",
  "/maintenance/[id]/edit/page": "app/maintenance/[id]/edit/page.js",
  "/maintenance/new/page": "app/maintenance/new/page.js",
  "/maintenance/page": "app/maintenance/page.js",
  "/page": "app/page.js",
  "/messages/page": "app/messages/page.js",
  "/mortgage/page": "app/mortgage/page.js",
  "/market/page": "app/market/page.js",
  "/payments/new/page": "app/payments/new/page.js",
  "/payments/page": "app/payments/page.js",
  "/portal/auth/callback/route": "app/portal/auth/callback/route.js",
  "/portal/dashboard/page": "app/portal/dashboard/page.js",
  "/portal/documents/page": "app/portal/documents/page.js",
  "/portal/maintenance/page": "app/portal/maintenance/page.js",
  "/portal/page": "app/portal/page.js",
  "/portal/messages/page": "app/portal/messages/page.js",
  "/portal/payments/page": "app/portal/payments/page.js",
  "/properties/[id]/edit/page": "app/properties/[id]/edit/page.js",
  "/properties/[id]/page": "app/properties/[id]/page.js",
  "/properties/new/page": "app/properties/new/page.js",
  "/properties/page": "app/properties/page.js",
  "/quickbooks/page": "app/quickbooks/page.js",
  "/reports/page": "app/reports/page.js",
  "/reset-password/page": "app/reset-password/page.js",
  "/screening/page": "app/screening/page.js",
  "/signup/page": "app/signup/page.js",
  "/share/[token]/page": "app/share/[token]/page.js",
  "/tax/page": "app/tax/page.js",
  "/tenants/[id]/edit/page": "app/tenants/[id]/edit/page.js",
  "/tenants/[id]/page": "app/tenants/[id]/page.js",
  "/tenants/new/page": "app/tenants/new/page.js",
  "/tenants/page": "app/tenants/page.js",
  "/turnover/page": "app/turnover/page.js",
  "/api/billing/portal/route": "app/api/billing/portal/route.js",
  "/api/billing/checkout/route": "app/api/billing/checkout/route.js",
  "/api/billing/confirm/route": "app/api/billing/confirm/route.js",
  "/api/cron/sync-billing/route": "app/api/cron/sync-billing/route.js",
  "/api/design/approve/route": "app/api/design/approve/route.js",
  "/api/design/board/route": "app/api/design/board/route.js",
  "/api/cron/generate-rent/route": "app/api/cron/generate-rent/route.js",
  "/api/stripe/account-status/route": "app/api/stripe/account-status/route.js",
  "/api/stripe/checkout/route": "app/api/stripe/checkout/route.js",
  "/api/stripe/confirm/route": "app/api/stripe/confirm/route.js",
  "/api/stripe/webhook/route": "app/api/stripe/webhook/route.js",
  "/api/stripe/connect/route": "app/api/stripe/connect/route.js",
  "/api/cron/digest/route": "app/api/cron/digest/route.js",
  "/api/design/scrape/route": "app/api/design/scrape/route.js"
}